calculator.py
calculator_anarim1-0.0.1.dist-info/LICENSE.txt
calculator_anarim1-0.0.1.dist-info/METADATA
calculator_anarim1-0.0.1.dist-info/WHEEL
calculator_anarim1-0.0.1.dist-info/top_level.txt
calculator_anarim1-0.0.1.dist-info/RECORD
