Metadata-Version: 2.1
Name: calculator-anarim1
Version: 0.0.1
Summary: Simple Calculator with memory
Home-page: https://github.com/NaUrovne/calculator
Author: Albert Narimanov
Author-email: albertnarimanov@gmail.com
License: UNKNOWN
Platform: UNKNOWN
Provides-Extra: dev
Requires-Dist: pytest (>=3.7) ; extra == 'dev'
